agentshell/__init__.py
agentshell/action.py
agentshell/main.py
agentshell-0.0.7.dist-info/LICENSE
agentshell-0.0.7.dist-info/METADATA
agentshell-0.0.7.dist-info/WHEEL
agentshell-0.0.7.dist-info/top_level.txt
agentshell-0.0.7.dist-info/RECORD
