Metadata-Version: 2.1
Name: agentshell
Version: 0.0.7
Summary: A shell for your agent.
Home-page: https://github.com/AutonomousResearchGroup/agentshell
Author: Moon
Author-email: shawmakesmagic@gmail.com
License: MIT
Classifier: Development Status :: 2 - Pre-Alpha
Classifier: Intended Audience :: Science/Research
Classifier: License :: OSI Approved :: MIT License
Classifier: Programming Language :: Python :: 3
Classifier: Operating System :: POSIX :: Linux
Classifier: Operating System :: MacOS :: MacOS X
Classifier: Operating System :: Microsoft :: Windows
License-File: LICENSE
Requires-Dist: agentmemory
Requires-Dist: easycompletion
